Calculatorpy/Cal.py
Calculatorpy/__init__.py
Calculatorpy-1.0.dist-info/LICENCE
Calculatorpy-1.0.dist-info/METADATA
Calculatorpy-1.0.dist-info/WHEEL
Calculatorpy-1.0.dist-info/top_level.txt
Calculatorpy-1.0.dist-info/RECORD
