Metadata-Version: 2.1
Name: Calculatorpy
Version: 1.0
Summary: QrCode Scanner
Home-page: UNKNOWN
Author: Rahul Shah
Author-email: rahul.shah102006@gmail.com
License: MIT
Platform: UNKNOWN
Classifier: License :: OSI Approved :: MIT License
Classifier: Programming Language :: Python :: 3.6
Classifier: Programming Language :: Python :: 3.7
Classifier: Programming Language :: Python :: 3.8
